sstudentt/__init__.py
sstudentt/sstudentt.py
sstudentt-0.1.1.dist-info/AUTHORS.rst
sstudentt-0.1.1.dist-info/LICENSE
sstudentt-0.1.1.dist-info/METADATA
sstudentt-0.1.1.dist-info/WHEEL
sstudentt-0.1.1.dist-info/top_level.txt
sstudentt-0.1.1.dist-info/RECORD
