Metadata-Version: 2.1
Name: sstudentt
Version: 0.1.1
Summary: An implementation of the skewed student-t distribution.
Home-page: https://github.com/berrij/sstudentt
Author: Jonathan Berrisch
Author-email: jonathan@berrisch.biz
License: GNU General Public License v3
Keywords: sstudentt
Platform: UNKNOWN
Classifier: Development Status :: 4 - Beta
Classifier: Intended Audience :: Developers
Classifier: License :: OSI Approved :: GNU General Public License v3 (GPLv3)
Classifier: Natural Language :: English
Classifier: Programming Language :: Python :: 3
Classifier: Programming Language :: Python :: 3.7
Classifier: Programming Language :: Python :: 3.8
Requires-Python: >=3.6
License-File: LICENSE
License-File: AUTHORS.rst
Requires-Dist: numpy
Requires-Dist: scipy
